setup.py
bottledollarstoreflask/__init__.py
bottledollarstoreflask.egg-info/PKG-INFO
bottledollarstoreflask.egg-info/SOURCES.txt
bottledollarstoreflask.egg-info/dependency_links.txt
bottledollarstoreflask.egg-info/not-zip-safe
bottledollarstoreflask.egg-info/top_level.txt