Metadata-Version: 2.1
Name: bottledollarstoreflask
Version: 0.2
Summary: dollar store flask
Home-page: https://github.com/rigityrooahhdev/bottle
Author: rigityrooahhdev
Author-email: rigityrooahh.dev@gmail.com
License: MIT
